target_bigquery/__init__.py
target_bigquery/main.py
target_bigquery/schema.py
target_bigquery/sync.py
target_bigquery_partition-0.2.4.dist-info/licenses/AUTHORS.md
target_bigquery_partition-0.2.4.dist-info/licenses/LICENSE
target_bigquery_partition-0.2.4.dist-info/METADATA
target_bigquery_partition-0.2.4.dist-info/WHEEL
target_bigquery_partition-0.2.4.dist-info/entry_points.txt
target_bigquery_partition-0.2.4.dist-info/top_level.txt
target_bigquery_partition-0.2.4.dist-info/RECORD
